README.rst
setup.py
mpesa/__init__.py
mpesa/src.py
mpesa.egg-info/PKG-INFO
mpesa.egg-info/SOURCES.txt
mpesa.egg-info/dependency_links.txt
mpesa.egg-info/requires.txt
mpesa.egg-info/top_level.txt