Metadata-Version: 1.2
Name: mpesa
Version: 0.0.1
Summary: a pip installable mpesa package
Home-page: UNKNOWN
Author: Sheila Wambui Karienye
Author-email: sheila.karienye@gmail.com
License: UNKNOWN
Keywords: mpesa API module
Platform: UNKNOWN
Requires-Python: >=2.6
